[{"word": "Origlnal Message :", "bounding_box": [111, 143, 195, 155]}, {"word": "Zineer Lorl", "bounding_box": [136, 154, 186, 162]}, {"word": "Sent:", "bounding_box": [94, 166, 120, 174]}, {"word": "Nloncav, Octobe", "bounding_box": [136, 166, 206, 174]}, {"word": "04, 1299221 PM", "bounding_box": [211, 163, 289, 177]}, {"word": "1", "bounding_box": [696, 107, 716, 225]}, {"word": "Osbore Kevin (PMMC", "bounding_box": [134, 174, 239, 189]}, {"word": "Sublect: RE:", "bounding_box": [93, 187, 157, 199]}, {"word": "708 EE -Marlboro", "bounding_box": [165, 187, 241, 199]}, {"word": "Mirio", "bounding_box": [244, 188, 268, 196]}, {"word": "Ranch", "bounding_box": [274, 188, 302, 196]}, {"word": "What item is this?", "bounding_box": [95, 211, 193, 225]}, {"word": "From:", "bounding_box": [92, 152, 122, 165]}, {"word": "Logah", "bounding_box": [236, 174, 266, 187]}]